gptloop/__init__.py
gptloop/cli.py
gptloop-0.0.4.dist-info/LICENSE
gptloop-0.0.4.dist-info/METADATA
gptloop-0.0.4.dist-info/WHEEL
gptloop-0.0.4.dist-info/entry_points.txt
gptloop-0.0.4.dist-info/top_level.txt
gptloop-0.0.4.dist-info/RECORD
