Metadata-Version: 2.1
Name: gptloop
Version: 0.0.4
Summary: GPTLoop is a versatile AI-powered assistant to enhance work quality and efficiency
Home-page: https://github.com/mcai/GPTLoop
Author: Min Cai
Author-email: min.cai.china@gmail.com
Classifier: Development Status :: 2 - Pre-Alpha
Classifier: Intended Audience :: Developers
Classifier: License :: OSI Approved :: MIT License
Classifier: Programming Language :: Python :: 3
Classifier: Programming Language :: Python :: 3.6
Classifier: Programming Language :: Python :: 3.7
Classifier: Programming Language :: Python :: 3.8
Classifier: Programming Language :: Python :: 3.9
Classifier: Programming Language :: Python :: 3.10
Classifier: Programming Language :: Python :: 3.11
Classifier: Topic :: Software Development :: Libraries :: Application Frameworks
Classifier: Topic :: Software Development :: Libraries :: Python Modules
Requires-Python: >=3.6
License-File: LICENSE
Requires-Dist: langchain (==0.0.144)
Requires-Dist: openai (==0.27.4)
